etler/__init__.py
etler/config.py
etler/settings.yml
etler/extract/__init__.py
etler/load/__init__.py
etler/transform/__init__.py
etler/transform/cutter.py
etler-0.0.3.dist-info/LICENSE
etler-0.0.3.dist-info/WHEEL
etler-0.0.3.dist-info/METADATA
etler-0.0.3.dist-info/RECORD
