Metadata-Version: 2.1
Name: etler
Version: 0.0.3
Summary: etler - ETL Utilities
Home-page: https://github.com/sdll/etler
License: UNKNOWN
Author: Sasha Illarionov
Author-email: sasha@sdll.space
Classifier: License :: OSI Approved :: MIT License
